logconfig/loaders.py
logconfig/_compat.py
logconfig/utils.py
logconfig/__init__.py
logconfig/exceptions.py
logconfig/__meta__.py
logconfig-0.4.0.dist-info/METADATA
logconfig-0.4.0.dist-info/DESCRIPTION.rst
logconfig-0.4.0.dist-info/metadata.json
logconfig-0.4.0.dist-info/top_level.txt
logconfig-0.4.0.dist-info/WHEEL
logconfig-0.4.0.dist-info/RECORD
