Metadata-Version: 2.0
Name: logconfig
Version: 0.4.0
Summary: Simple helper moudle for configuring Python logging
Home-page: https://github.com/dgilland/logconfig
Author: Derrick Gilland
Author-email: dgilland@gmail.com
License: MIT License
Keywords: logging config configuration
Platform: UNKNOWN
Classifier: Development Status :: 4 - Beta
Classifier: Intended Audience :: Developers
Classifier: Intended Audience :: System Administrators
Classifier: Operating System :: OS Independent
Classifier: Programming Language :: Python
Classifier: License :: OSI Approved :: MIT License
Classifier: Topic :: Software Development :: Libraries :: Python Modules
Classifier: Topic :: System :: Logging
Classifier: Topic :: System :: Systems Administration
Classifier: Programming Language :: Python
Classifier: Programming Language :: Python :: 2
Classifier: Programming Language :: Python :: 2.6
Classifier: Programming Language :: Python :: 2.7
Classifier: Programming Language :: Python :: 3
Classifier: Programming Language :: Python :: 3.2
Classifier: Programming Language :: Python :: 3.3
Classifier: Programming Language :: Python :: 3.4
Requires-Dist: PyYAML (>=3.11)
Requires-Dist: logutils (>=0.3.3)
